Randomobject/__init__.py
Randomobject/core.py
randomobject-0.1.0.dist-info/licenses/LICENSE
randomobject-0.1.0.dist-info/METADATA
randomobject-0.1.0.dist-info/WHEEL
randomobject-0.1.0.dist-info/top_level.txt
randomobject-0.1.0.dist-info/RECORD
