Metadata-Version: 2.4
Name: Randomobject
Version: 0.1.0
Summary: A simple random object selector
Author-email: Your Name <your@email.com>
License: MIT
Classifier: Programming Language :: Python :: 3
Classifier: License :: OSI Approved :: MIT License
Classifier: Operating System :: OS Independent
Requires-Python: >=3.7
License-File: LICENSE
Dynamic: license-file
